hanziPhon/__init__.py
hanziPhon/guang.py
hanziPhon/moe.py
hanziPhon/data/GuangYun.json
hanziPhon/data/moe_char_phon.json
hanziPhon/data/moe_transcriptions.csv
hanziPhon-0.0.4.dist-info/METADATA
hanziPhon-0.0.4.dist-info/WHEEL
hanziPhon-0.0.4.dist-info/top_level.txt
hanziPhon-0.0.4.dist-info/RECORD
