Metadata-Version: 2.1
Name: hanziPhon
Version: 0.0.4
Summary: Hanzi phonetic interface
Home-page: https://github.com/liao961120/hanziPhon
Author: Yongfu Liao
Author-email: liao961120@gmail.com
License: UNKNOWN
Platform: UNKNOWN
Classifier: Programming Language :: Python :: 3
Classifier: License :: OSI Approved :: MIT License
Classifier: Operating System :: OS Independent
Requires-Python: >=3.7
